openCSG/__init__.py
openCSG/geom.py
openCSG-0.0.2.dist-info/LICENSE
openCSG-0.0.2.dist-info/METADATA
openCSG-0.0.2.dist-info/WHEEL
openCSG-0.0.2.dist-info/entry_points.txt
openCSG-0.0.2.dist-info/top_level.txt
openCSG-0.0.2.dist-info/RECORD
